[
  {
    "id": "nextjs-pro",
    "scope": "collection",
    "name": "Next.js Pro Development",
    "description": "Complete set of prompts and agents for professional Next.js development with React, TypeScript, and best practices",
    "version": "1.0.0",
    "category": "development",
    "tags": ["nextjs", "react", "typescript", "web"],
    "icon": "⚛️",
    "official": true,
    "packages": [
      {
        "packageId": "nextjs-expert",
        "required": true,
        "reason": "Core Next.js development patterns and best practices"
      },
      {
        "packageId": "react-hooks",
        "required": true,
        "reason": "React hooks patterns and custom hook development"
      },
      {
        "packageId": "typescript-strict",
        "required": true,
        "reason": "TypeScript configuration and type safety"
      },
      {
        "packageId": "tailwind-css",
        "required": false,
        "reason": "Tailwind CSS styling utilities and patterns"
      },
      {
        "packageId": "api-routes",
        "required": false,
        "reason": "Next.js API routes and serverless functions"
      }
    ]
  },
  {
    "id": "python-data",
    "scope": "collection",
    "name": "Python Data Science Stack",
    "description": "Essential tools for data science and machine learning with Python, including pandas, numpy, and scikit-learn",
    "version": "1.0.0",
    "category": "data-science",
    "tags": ["python", "data-science", "ml", "pandas"],
    "icon": "🐍",
    "official": true,
    "packages": [
      {
        "packageId": "python-expert",
        "required": true,
        "reason": "Python best practices and coding standards"
      },
      {
        "packageId": "pandas-helper",
        "required": true,
        "reason": "DataFrame operations and data manipulation"
      },
      {
        "packageId": "numpy-arrays",
        "required": true,
        "reason": "Numerical computing and array operations"
      },
      {
        "packageId": "data-visualization",
        "required": false,
        "reason": "Matplotlib and seaborn plotting helpers"
      },
      {
        "packageId": "ml-sklearn",
        "required": false,
        "reason": "Machine learning model development and training"
      }
    ]
  },
  {
    "id": "vue-fullstack",
    "scope": "collection",
    "name": "Vue.js Full Stack",
    "description": "Complete Vue.js ecosystem including Nuxt.js, Pinia, and Vue Router for building modern web applications",
    "version": "1.0.0",
    "category": "development",
    "tags": ["vue", "nuxt", "frontend", "web"],
    "icon": "💚",
    "official": true,
    "packages": [
      {
        "packageId": "vue-expert",
        "required": true,
        "reason": "Vue 3 composition API and patterns"
      },
      {
        "packageId": "nuxt-framework",
        "required": true,
        "reason": "Nuxt.js server-side rendering and routing"
      },
      {
        "packageId": "pinia-store",
        "required": true,
        "reason": "State management with Pinia"
      },
      {
        "packageId": "vue-router",
        "required": false,
        "reason": "Advanced routing patterns"
      },
      {
        "packageId": "vite-config",
        "required": false,
        "reason": "Vite build configuration and optimization"
      }
    ]
  },
  {
    "id": "devops-essentials",
    "scope": "collection",
    "name": "DevOps Essentials",
    "description": "Core DevOps tools and practices including Docker, Kubernetes, CI/CD, and infrastructure as code",
    "version": "1.0.0",
    "category": "devops",
    "tags": ["devops", "docker", "kubernetes", "ci-cd"],
    "icon": "🚀",
    "official": true,
    "packages": [
      {
        "packageId": "docker-expert",
        "required": true,
        "reason": "Docker containerization and best practices"
      },
      {
        "packageId": "kubernetes-guide",
        "required": true,
        "reason": "K8s deployment and orchestration"
      },
      {
        "packageId": "github-actions",
        "required": true,
        "reason": "CI/CD pipeline configuration"
      },
      {
        "packageId": "terraform-iac",
        "required": false,
        "reason": "Infrastructure as code with Terraform"
      },
      {
        "packageId": "monitoring-logging",
        "required": false,
        "reason": "Application monitoring and log management"
      }
    ]
  },
  {
    "id": "testing-suite",
    "scope": "collection",
    "name": "Complete Testing Suite",
    "description": "Comprehensive testing tools including unit tests, integration tests, and E2E testing frameworks",
    "version": "1.0.0",
    "category": "testing",
    "tags": ["testing", "jest", "playwright", "vitest"],
    "icon": "🧪",
    "official": true,
    "packages": [
      {
        "packageId": "jest-testing",
        "required": true,
        "reason": "Jest unit and integration testing"
      },
      {
        "packageId": "playwright-e2e",
        "required": true,
        "reason": "End-to-end browser testing"
      },
      {
        "packageId": "vitest-unit",
        "required": false,
        "reason": "Vite-native unit testing"
      },
      {
        "packageId": "testing-library",
        "required": false,
        "reason": "React Testing Library for component tests"
      },
      {
        "packageId": "coverage-reports",
        "required": false,
        "reason": "Test coverage configuration and reporting"
      }
    ]
  },
  {
    "id": "rust-systems",
    "scope": "collection",
    "name": "Rust Systems Programming",
    "description": "Rust development for systems programming, CLI tools, and high-performance applications",
    "version": "1.0.0",
    "category": "development",
    "tags": ["rust", "systems", "performance", "cli"],
    "icon": "🦀",
    "official": true,
    "packages": [
      {
        "packageId": "rust-expert",
        "required": true,
        "reason": "Rust ownership, borrowing, and memory safety"
      },
      {
        "packageId": "cargo-workspace",
        "required": true,
        "reason": "Cargo workspace management and dependencies"
      },
      {
        "packageId": "async-rust",
        "required": false,
        "reason": "Async/await patterns with Tokio"
      },
      {
        "packageId": "cli-building",
        "required": false,
        "reason": "CLI application development with clap"
      },
      {
        "packageId": "rust-performance",
        "required": false,
        "reason": "Performance optimization and profiling"
      }
    ]
  },
  {
    "id": "mobile-flutter",
    "scope": "collection",
    "name": "Flutter Mobile Development",
    "description": "Cross-platform mobile app development with Flutter and Dart for iOS and Android",
    "version": "1.0.0",
    "category": "development",
    "tags": ["flutter", "dart", "mobile", "ios", "android"],
    "icon": "📱",
    "official": true,
    "packages": [
      {
        "packageId": "flutter-expert",
        "required": true,
        "reason": "Flutter widget tree and state management"
      },
      {
        "packageId": "dart-language",
        "required": true,
        "reason": "Dart language patterns and async programming"
      },
      {
        "packageId": "flutter-navigation",
        "required": true,
        "reason": "Navigation and routing patterns"
      },
      {
        "packageId": "state-management",
        "required": false,
        "reason": "Riverpod/Provider state management"
      },
      {
        "packageId": "flutter-testing",
        "required": false,
        "reason": "Widget and integration testing"
      }
    ]
  },
  {
    "id": "documentation",
    "scope": "collection",
    "name": "Documentation & Writing",
    "description": "Tools for technical writing, documentation, and creating clear, comprehensive guides",
    "version": "1.0.0",
    "category": "documentation",
    "tags": ["docs", "writing", "markdown", "technical"],
    "icon": "📝",
    "official": true,
    "packages": [
      {
        "packageId": "technical-writer",
        "required": true,
        "reason": "Technical writing style and structure"
      },
      {
        "packageId": "api-documentation",
        "required": true,
        "reason": "API documentation and OpenAPI specs"
      },
      {
        "packageId": "readme-generator",
        "required": false,
        "reason": "Generate comprehensive README files"
      },
      {
        "packageId": "changelog-writer",
        "required": false,
        "reason": "Maintain changelogs and release notes"
      },
      {
        "packageId": "code-comments",
        "required": false,
        "reason": "Write clear code comments and JSDoc"
      }
    ]
  },
  {
    "id": "golang-backend",
    "scope": "collection",
    "name": "Go Backend Development",
    "description": "Build robust backend services and APIs with Go, including microservices and gRPC",
    "version": "1.0.0",
    "category": "development",
    "tags": ["golang", "backend", "api", "microservices"],
    "icon": "🐹",
    "official": true,
    "packages": [
      {
        "packageId": "golang-expert",
        "required": true,
        "reason": "Go language patterns and idiomatic code"
      },
      {
        "packageId": "go-http-server",
        "required": true,
        "reason": "HTTP servers and REST API development"
      },
      {
        "packageId": "go-concurrency",
        "required": true,
        "reason": "Goroutines, channels, and concurrent patterns"
      },
      {
        "packageId": "grpc-services",
        "required": false,
        "reason": "gRPC service development and protobuf"
      },
      {
        "packageId": "go-testing",
        "required": false,
        "reason": "Testing patterns and table-driven tests"
      }
    ]
  },
  {
    "id": "frontend-design",
    "scope": "collection",
    "name": "Frontend UI/UX Design",
    "description": "Design systems, component libraries, and modern UI development with accessibility",
    "version": "1.0.0",
    "category": "design",
    "tags": ["design", "ui", "ux", "accessibility"],
    "icon": "🎨",
    "official": true,
    "packages": [
      {
        "packageId": "design-systems",
        "required": true,
        "reason": "Build and maintain design systems"
      },
      {
        "packageId": "component-library",
        "required": true,
        "reason": "Reusable component development"
      },
      {
        "packageId": "accessibility-a11y",
        "required": true,
        "reason": "WCAG compliance and accessibility patterns"
      },
      {
        "packageId": "css-architecture",
        "required": false,
        "reason": "CSS organization and naming conventions"
      },
      {
        "packageId": "responsive-design",
        "required": false,
        "reason": "Mobile-first responsive layouts"
      }
    ]
  }
]
